<?xml version='1.0' encoding='ISO-8859-1'?>
 <siteData xmlns:xsi="http://www.w3.org/2001/XMLSchema-instance" xsi:noNamespaceSchemaLocation="http://dd.weather.gc.ca/citypage_weather/schema/site.xsd">
 <license>http://dd.weather.gc.ca/doc/LICENCE_GENERAL.txt</license>
 <dateTime name="xmlCreation" zone="UTC" UTCOffset="0">
 <year>2016</year>
 <month name="October">10</month>
 <day name="Friday">14</day>
 <hour>14</hour>
 <minute>04</minute>
 <timeStamp>20161014140400</timeStamp>
 <textSummary>Friday October 14, 2016 at 14:04 UTC</textSummary>
 </dateTime>
 <dateTime name="xmlCreation" zone="ADT" UTCOffset="-3">
 <year>2016</year>
 <month name="October">10</month>
 <day name="Friday">14</day>
 <hour>11</hour>
 <minute>04</minute>
 <timeStamp>20161014110400</timeStamp>
 <textSummary>Friday October 14, 2016 at 11:04 ADT</textSummary>
 </dateTime>
 <location>
 <continent>North America</continent>
 <country code="ca">Canada</country>
 <province code="nb">New Brunswick</province>
 <name code="s0000200" lat="47.17N" lon="67.92W">St. Leonard</name>
 <region>Edmundston and Madawaska County</region>
 </location>
 <warnings url="http://weather.gc.ca/warnings/report_e.html?nb1">
 <event type="statement" priority="low" description="FROST ADVISORY IN EFFECT">
 <dateTime name="eventIssue" zone="UTC" UTCOffset="0">
 <year>2016</year>
 <month name="October">10</month>
 <day name="Friday">14</day>
 <hour>13</hour>
 <minute>21</minute>
 <timeStamp>20161014132100</timeStamp>
 <textSummary>Friday October 14, 2016 at 13:21 UTC</textSummary>
 </dateTime>
 <dateTime name="eventIssue" zone="ADT" UTCOffset="-3">
 <year>2016</year>
 <month name="October">10</month>
 <day name="Friday">14</day>
 <hour>10</hour>
 <minute>21</minute>
 <timeStamp>20161014102100</timeStamp>
 <textSummary>Friday October 14, 2016 at 10:21 ADT</textSummary>
 </dateTime>
 </event>
 </warnings>
 <currentConditions>
 <station code="ysl" lat="47.16N" lon="67.84W">St. Leonard Airport</station>
 <dateTime name="observation" zone="UTC" UTCOffset="0">
 <year>2016</year>
 <month name="October">10</month>
 <day name="Friday">14</day>
 <hour>14</hour>
 <minute>00</minute>
 <timeStamp>20161014140000</timeStamp>
 <textSummary>Friday October 14, 2016 at 14:00 UTC</textSummary>
 </dateTime>
 <dateTime name="observation" zone="ADT" UTCOffset="-3">
 <year>2016</year>
 <month name="October">10</month>
 <day name="Friday">14</day>
 <hour>11</hour>
 <minute>00</minute>
 <timeStamp>20161014110000</timeStamp>
 <textSummary>Friday October 14, 2016 at 11:00 ADT</textSummary>
 </dateTime>
 <condition/>
 <iconCode format="gif"/>
 <temperature unitType="metric" units="C">4.2</temperature>
 <dewpoint unitType="metric" units="C">-3.1</dewpoint>
 <pressure unitType="metric" units="kPa" change="0.24" tendency="rising">102.4</pressure>
 <visibility unitType="metric" units="km"/>
 <relativeHumidity units="%">59</relativeHumidity>
 <wind>
 <speed unitType="metric" units="km/h">31</speed>
 <gust unitType="metric" units="km/h"/>
 <direction>NW</direction>
 <bearing units="degrees">322.0</bearing>
 </wind>
 </currentConditions>
 <forecastGroup>
 <dateTime name="forecastIssue" zone="UTC" UTCOffset="0">
 <year>2016</year>
 <month name="October">10</month>
 <day name="Friday">14</day>
 <hour>14</hour>
 <minute>00</minute>
 <timeStamp>20161014140000</timeStamp>
 <textSummary>Friday October 14, 2016 at 14:00 UTC</textSummary>
 </dateTime>
 <dateTime name="forecastIssue" zone="ADT" UTCOffset="-3">
 <year>2016</year>
 <month name="October">10</month>
 <day name="Friday">14</day>
 <hour>11</hour>
 <minute>00</minute>
 <timeStamp>20161014110000</timeStamp>
 <textSummary>Friday October 14, 2016 at 11:00 ADT</textSummary>
 </dateTime>
 <regionalNormals>
 <textSummary>Low plus 1. High 10.</textSummary>
 <temperature unitType="metric" units="C" class="high">10</temperature>
 <temperature unitType="metric" units="C" class="low">1</temperature>
 </regionalNormals>
 <forecast>
 <period textForecastName="Today">Friday</period>
 <textSummary>Mainly sunny. Wind northwest 20 km/h gusting to 40 becoming light this afternoon. High 8. UV index 3 or moderate.</textSummary>
 <cloudPrecip>
 <textSummary>Mainly sunny.</textSummary>
 </cloudPrecip>
 <abbreviatedForecast>
 <iconCode format="gif">01</iconCode>
 <pop units="%"/>
 <textSummary>Mainly sunny</textSummary>
 </abbreviatedForecast>
 <temperatures>
 <textSummary>High 8.</textSummary>
 <temperature unitType="metric" units="C" class="high">8</temperature>
 </temperatures>
 <winds>
 <textSummary>Wind northwest 20 km/h gusting to 40 becoming light this afternoon.</textSummary>
 <wind index="1" rank="major">
 <speed unitType="metric" units="km/h">20</speed>
 <gust unitType="metric" units="km/h">40</gust>
 <direction>NW</direction>
 <bearing units="degrees">32</bearing>
 </wind>
 <wind index="2" rank="major">
 <speed unitType="metric" units="km/h">10</speed>
 <gust unitType="metric" units="km/h">00</gust>
 <direction>NW</direction>
 <bearing units="degrees">32</bearing>
 </wind>
 </winds>
 <precipitation>
 <textSummary/>
 <precipType start="" end=""/>
 </precipitation>
 <uv category="moderate">
 <index>3</index>
 <textSummary>UV index 3 or moderate.</textSummary>
 </uv>
 <relativeHumidity units="%">40</relativeHumidity>
 </forecast>
 <forecast>
 <period textForecastName="Tonight">Friday night</period>
 <textSummary>A few clouds. Low minus 2 with frost.</textSummary>
 <cloudPrecip>
 <textSummary>A few clouds.</textSummary>
 </cloudPrecip>
 <abbreviatedForecast>
 <iconCode format="gif">31</iconCode>
 <pop units="%"/>
 <textSummary>A few clouds</textSummary>
 </abbreviatedForecast>
 <temperatures>
 <textSummary>Low minus 2 with frost.</textSummary>
 <temperature unitType="metric" units="C" class="low">-2</temperature>
 </temperatures>
 <winds/>
 <precipitation>
 <textSummary/>
 <precipType start="" end=""/>
 </precipitation>
 <relativeHumidity units="%">75</relativeHumidity>
 <frost>
 <textSummary>frost.</textSummary>
 </frost>
 </forecast>
 <forecast>
 <period textForecastName="Saturday">Saturday</period>
 <textSummary>Sunny. High 11.</textSummary>
 <cloudPrecip>
 <textSummary>Sunny.</textSummary>
 </cloudPrecip>
 <abbreviatedForecast>
 <iconCode format="gif">00</iconCode>
 <pop units="%"/>
 <textSummary>Sunny</textSummary>
 </abbreviatedForecast>
 <temperatures>
 <textSummary>High 11.</textSummary>
 <temperature unitType="metric" units="C" class="high">11</temperature>
 </temperatures>
 <winds/>
 <precipitation>
 <textSummary/>
 <precipType start="" end=""/>
 </precipitation>
 <relativeHumidity units="%">40</relativeHumidity>
 </forecast>
 <forecast>
 <period textForecastName="Saturday night">Saturday night</period>
 <textSummary>Cloudy. Low plus 4.</textSummary>
 <cloudPrecip>
 <textSummary>Cloudy.</textSummary>
 </cloudPrecip>
 <abbreviatedForecast>
 <iconCode format="gif">10</iconCode>
 <pop units="%"/>
 <textSummary>Cloudy</textSummary>
 </abbreviatedForecast>
 <temperatures>
 <textSummary>Low plus 4.</textSummary>
 <temperature unitType="metric" units="C" class="low">4</temperature>
 </temperatures>
 <winds/>
 <precipitation>
 <textSummary/>
 <precipType start="" end=""/>
 </precipitation>
 <relativeHumidity units="%">65</relativeHumidity>
 </forecast>
 <forecast>
 <period textForecastName="Sunday">Sunday</period>
 <textSummary>Cloudy with 40 percent chance of showers. High 15.</textSummary>
 <cloudPrecip>
 <textSummary>Cloudy with 40 percent chance of showers.</textSummary>
 </cloudPrecip>
 <abbreviatedForecast>
 <iconCode format="gif">12</iconCode>
 <pop units="%">40</pop>
 <textSummary>Chance of showers</textSummary>
 </abbreviatedForecast>
 <temperatures>
 <textSummary>High 15.</textSummary>
 <temperature unitType="metric" units="C" class="high">15</temperature>
 </temperatures>
 <winds/>
 <precipitation>
 <textSummary/>
 <precipType start="66" end="69">rain</precipType>
 </precipitation>
 <relativeHumidity units="%">70</relativeHumidity>
 </forecast>
 <forecast>
 <period textForecastName="Sunday night">Sunday night</period>
 <textSummary>Cloudy periods with 60 percent chance of showers. Low 6.</textSummary>
 <cloudPrecip>
 <textSummary>Cloudy periods with 60 percent chance of showers.</textSummary>
 </cloudPrecip>
 <abbreviatedForecast>
 <iconCode format="gif">36</iconCode>
 <pop units="%">60</pop>
 <textSummary>Chance of showers</textSummary>
 </abbreviatedForecast>
 <temperatures>
 <textSummary>Low 6.</textSummary>
 <temperature unitType="metric" units="C" class="low">6</temperature>
 </temperatures>
 <winds/>
 <precipitation>
 <textSummary/>
 <precipType start="69" end="72">rain</precipType>
 </precipitation>
 <relativeHumidity units="%">100</relativeHumidity>
 </forecast>
 <forecast>
 <period textForecastName="Monday">Monday</period>
 <textSummary>Sunny. High 13.</textSummary>
 <cloudPrecip>
 <textSummary>Sunny.</textSummary>
 </cloudPrecip>
 <abbreviatedForecast>
 <iconCode format="gif">00</iconCode>
 <pop units="%"/>
 <textSummary>Sunny</textSummary>
 </abbreviatedForecast>
 <temperatures>
 <textSummary>High 13.</textSummary>
 <temperature unitType="metric" units="C" class="high">13</temperature>
 </temperatures>
 <winds/>
 <precipitation>
 <textSummary/>
 <precipType start="" end=""/>
 </precipitation>
 <relativeHumidity units="%">45</relativeHumidity>
 </forecast>
 <forecast>
 <period textForecastName="Monday night">Monday night</period>
 <textSummary>Increasing cloudiness. Low plus 2.</textSummary>
 <cloudPrecip>
 <textSummary>Increasing cloudiness.</textSummary>
 </cloudPrecip>
 <abbreviatedForecast>
 <iconCode format="gif">32</iconCode>
 <pop units="%"/>
 <textSummary>Cloudy periods</textSummary>
 </abbreviatedForecast>
 <temperatures>
 <textSummary>Low plus 2.</textSummary>
 <temperature unitType="metric" units="C" class="low">2</temperature>
 </temperatures>
 <winds/>
 <precipitation>
 <textSummary/>
 <precipType start="" end=""/>
 </precipitation>
 <relativeHumidity units="%">75</relativeHumidity>
 </forecast>
 <forecast>
 <period textForecastName="Tuesday">Tuesday</period>
 <textSummary>Cloudy with 60 percent chance of rain showers or flurries. High 6.</textSummary>
 <cloudPrecip>
 <textSummary>Cloudy with 60 percent chance of rain showers or flurries.</textSummary>
 </cloudPrecip>
 <abbreviatedForecast>
 <iconCode format="gif">15</iconCode>
 <pop units="%">60</pop>
 <textSummary>Chance of rain showers or flurries</textSummary>
 </abbreviatedForecast>
 <temperatures>
 <textSummary>High 6.</textSummary>
 <temperature unitType="metric" units="C" class="high">6</temperature>
 </temperatures>
 <winds/>
 <precipitation>
 <textSummary/>
 <precipType start="106" end="107">rain</precipType>
 <precipType start="107" end="112">rain and snow</precipType>
 </precipitation>
 <relativeHumidity units="%">95</relativeHumidity>
 </forecast>
 <forecast>
 <period textForecastName="Tuesday night">Tuesday night</period>
 <textSummary>Cloudy with 40 percent chance of showers. Low plus 4.</textSummary>
 <cloudPrecip>
 <textSummary>Cloudy with 40 percent chance of showers.</textSummary>
 </cloudPrecip>
 <abbreviatedForecast>
 <iconCode format="gif">12</iconCode>
 <pop units="%">40</pop>
 <textSummary>Chance of showers</textSummary>
 </abbreviatedForecast>
 <temperatures>
 <textSummary>Low plus 4.</textSummary>
 <temperature unitType="metric" units="C" class="low">4</temperature>
 </temperatures>
 <winds/>
 <precipitation>
 <textSummary/>
 <precipType start="120" end="126">rain</precipType>
 </precipitation>
 <relativeHumidity units="%">95</relativeHumidity>
 </forecast>
 <forecast>
 <period textForecastName="Wednesday">Wednesday</period>
 <textSummary>Cloudy. High 13.</textSummary>
 <cloudPrecip>
 <textSummary>Cloudy.</textSummary>
 </cloudPrecip>
 <abbreviatedForecast>
 <iconCode format="gif">10</iconCode>
 <pop units="%"/>
 <textSummary>Cloudy</textSummary>
 </abbreviatedForecast>
 <temperatures>
 <textSummary>High 13.</textSummary>
 <temperature unitType="metric" units="C" class="high">13</temperature>
 </temperatures>
 <winds/>
 <precipitation>
 <textSummary/>
 <precipType start="" end=""/>
 </precipitation>
 <relativeHumidity units="%">80</relativeHumidity>
 </forecast>
 <forecast>
 <period textForecastName="Wednesday night">Wednesday night</period>
 <textSummary>Cloudy with 40 percent chance of showers. Low 8.</textSummary>
 <cloudPrecip>
 <textSummary>Cloudy with 40 percent chance of showers.</textSummary>
 </cloudPrecip>
 <abbreviatedForecast>
 <iconCode format="gif">12</iconCode>
 <pop units="%">40</pop>
 <textSummary>Chance of showers</textSummary>
 </abbreviatedForecast>
 <temperatures>
 <textSummary>Low 8.</textSummary>
 <temperature unitType="metric" units="C" class="low">8</temperature>
 </temperatures>
 <winds/>
 <precipitation>
 <textSummary/>
 <precipType start="144" end="150">rain</precipType>
 </precipitation>
 <relativeHumidity units="%">100</relativeHumidity>
 </forecast>
 <forecast>
 <period textForecastName="Thursday">Thursday</period>
 <textSummary>Cloudy. High 14.</textSummary>
 <cloudPrecip>
 <textSummary>Cloudy.</textSummary>
 </cloudPrecip>
 <abbreviatedForecast>
 <iconCode format="gif">10</iconCode>
 <pop units="%"/>
 <textSummary>Cloudy</textSummary>
 </abbreviatedForecast>
 <temperatures>
 <textSummary>High 14.</textSummary>
 <temperature unitType="metric" units="C" class="high">14</temperature>
 </temperatures>
 <winds/>
 <precipitation>
 <textSummary/>
 <precipType start="" end=""/>
 </precipitation>
 <relativeHumidity units="%">75</relativeHumidity>
 </forecast>
 </forecastGroup>
 <yesterdayConditions>
 <temperature unitType="metric" units="C" class="high">17.3</temperature>
 <temperature unitType="metric" units="C" class="low">5.0</temperature>
 <precip unitType="metric" units="mm"/>
 </yesterdayConditions>
 <riseSet>
 <disclaimer>The information provided here, for the times of the rise and set of the sun, is an estimate included as a convenience to our clients. Values shown here may differ from the official sunrise/sunset data available from (http://hia-iha.nrc-cnrc.gc.ca/sunrise_e.html)</disclaimer>
 <dateTime name="sunrise" zone="UTC" UTCOffset="0">
 <year>2016</year>
 <month name="October">10</month>
 <day name="Friday">14</day>
 <hour>10</hour>
 <minute>49</minute>
 <timeStamp>20161014104900</timeStamp>
 <textSummary>Friday October 14, 2016 at 10:49 UTC</textSummary>
 </dateTime>
 <dateTime name="sunrise" zone="ADT" UTCOffset="-3">
 <year>2016</year>
 <month name="October">10</month>
 <day name="Friday">14</day>
 <hour>07</hour>
 <minute>49</minute>
 <timeStamp>20161014074900</timeStamp>
 <textSummary>Friday October 14, 2016 at 07:49 ADT</textSummary>
 </dateTime>
 <dateTime name="sunset" zone="UTC" UTCOffset="0">
 <year>2016</year>
 <month name="October">10</month>
 <day name="Friday">14</day>
 <hour>21</hour>
 <minute>46</minute>
 <timeStamp>20161014214600</timeStamp>
 <textSummary>Friday October 14, 2016 at 21:46 UTC</textSummary>
 </dateTime>
 <dateTime name="sunset" zone="ADT" UTCOffset="-3">
 <year>2016</year>
 <month name="October">10</month>
 <day name="Friday">14</day>
 <hour>18</hour>
 <minute>46</minute>
 <timeStamp>20161014184600</timeStamp>
 <textSummary>Friday October 14, 2016 at 18:46 ADT</textSummary>
 </dateTime>
 </riseSet>
 <almanac>
 <temperature class="extremeMax" period="1985-2013" unitType="metric" units="C" year="1995">22.5</temperature>
 <temperature class="extremeMin" period="1985-2013" unitType="metric" units="C" year="1993">-4.9</temperature>
 <temperature class="normalMax" unitType="metric" units="C">10.7</temperature>
 <temperature class="normalMin" unitType="metric" units="C">0.7</temperature>
 <temperature class="normalMean" unitType="metric" units="C">5.7</temperature>
 <precipitation class="extremeRainfall" period="1985-2013" unitType="metric" units="mm" year="1990">30.2</precipitation>
 <precipitation class="extremeSnowfall" period="1985-2013" unitType="metric" units="cm" year="1999">3.2</precipitation>
 <precipitation class="extremePrecipitation" period="1985-2013" unitType="metric" units="mm" year="1990">30.2</precipitation>
 <precipitation class="extremeSnowOnGround" period="1985-2013" unitType="metric" units="cm" year="1985">0.0</precipitation>
 <pop units="%">49.0</pop>
 </almanac>
 </siteData>

