<?xml version='1.0' encoding='ISO-8859-1'?>
 <siteData xmlns:xsi="http://www.w3.org/2001/XMLSchema-instance" xsi:noNamespaceSchemaLocation="http://dd.weather.gc.ca/citypage_weather/schema/site.xsd">
 <license>http://dd.weather.gc.ca/doc/LICENCE_GENERAL.txt</license>
 <dateTime name="xmlCreation" zone="UTC" UTCOffset="0">
 <year>2016</year>
 <month name="October">10</month>
 <day name="Friday">14</day>
 <hour>14</hour>
 <minute>39</minute>
 <timeStamp>20161014143900</timeStamp>
 <textSummary>Friday October 14, 2016 at 14:39 UTC</textSummary>
 </dateTime>
 <dateTime name="xmlCreation" zone="EDT" UTCOffset="-4">
 <year>2016</year>
 <month name="October">10</month>
 <day name="Friday">14</day>
 <hour>10</hour>
 <minute>39</minute>
 <timeStamp>20161014103900</timeStamp>
 <textSummary>Friday October 14, 2016 at 10:39 EDT</textSummary>
 </dateTime>
 <location>
 <continent>North America</continent>
 <country code="ca">Canada</country>
 <province code="qc">Quebec</province>
 <name code="s0000542" lat="55.28N" lon="77.75W">Kuujjuarapik</name>
 <region>Kuujjuarapik</region>
 </location>
 <warnings/>
 <currentConditions>
 <station code="ygw" lat="55.28N" lon="77.77W">Kuujjuarapik Airport</station>
 <dateTime name="observation" zone="UTC" UTCOffset="0">
 <year>2016</year>
 <month name="October">10</month>
 <day name="Friday">14</day>
 <hour>14</hour>
 <minute>39</minute>
 <timeStamp>20161014143900</timeStamp>
 <textSummary>Friday October 14, 2016 at 14:39 UTC</textSummary>
 </dateTime>
 <dateTime name="observation" zone="EDT" UTCOffset="-4">
 <year>2016</year>
 <month name="October">10</month>
 <day name="Friday">14</day>
 <hour>10</hour>
 <minute>39</minute>
 <timeStamp>20161014103900</timeStamp>
 <textSummary>Friday October 14, 2016 at 10:39 EDT</textSummary>
 </dateTime>
 <condition>Precipitation</condition>
 <iconCode format="gif">11</iconCode>
 <temperature unitType="metric" units="C">0.1</temperature>
 <dewpoint unitType="metric" units="C">-4.4</dewpoint>
 <pressure unitType="metric" units="kPa" change="" tendency="">101.7</pressure>
 <visibility unitType="metric" units="km">9.7</visibility>
 <relativeHumidity units="%">72</relativeHumidity>
 <wind>
 <speed unitType="metric" units="km/h">28</speed>
 <gust unitType="metric" units="km/h"/>
 <direction>WSW</direction>
 <bearing units="degrees">240.0</bearing>
 </wind>
 </currentConditions>
 <forecastGroup>
 <dateTime name="forecastIssue" zone="UTC" UTCOffset="0">
 <year>2016</year>
 <month name="October">10</month>
 <day name="Friday">14</day>
 <hour>08</hour>
 <minute>30</minute>
 <timeStamp>20161014083000</timeStamp>
 <textSummary>Friday October 14, 2016 at 08:30 UTC</textSummary>
 </dateTime>
 <dateTime name="forecastIssue" zone="EDT" UTCOffset="-4">
 <year>2016</year>
 <month name="October">10</month>
 <day name="Friday">14</day>
 <hour>04</hour>
 <minute>30</minute>
 <timeStamp>20161014043000</timeStamp>
 <textSummary>Friday October 14, 2016 at 04:30 EDT</textSummary>
 </dateTime>
 <regionalNormals>
 <textSummary>Low minus 1. High plus 5.</textSummary>
 <temperature unitType="metric" units="C" class="high">5</temperature>
 <temperature unitType="metric" units="C" class="low">-1</temperature>
 </regionalNormals>
 <forecast>
 <period textForecastName="Today">Friday</period>
 <textSummary>Flurries at times heavy. Wind west 30 km/h gusting to 50. High plus 1.</textSummary>
 <cloudPrecip>
 <textSummary>Flurries at times heavy.</textSummary>
 </cloudPrecip>
 <abbreviatedForecast>
 <iconCode format="gif">16</iconCode>
 <pop units="%"/>
 <textSummary>Flurries at times heavy</textSummary>
 </abbreviatedForecast>
 <temperatures>
 <textSummary>High plus 1.</textSummary>
 <temperature unitType="metric" units="C" class="high">1</temperature>
 </temperatures>
 <winds>
 <textSummary>Wind west 30 km/h gusting to 50.</textSummary>
 <wind index="1" rank="major">
 <speed unitType="metric" units="km/h">30</speed>
 <gust unitType="metric" units="km/h">50</gust>
 <direction>W</direction>
 <bearing units="degrees">27</bearing>
 </wind>
 </winds>
 <precipitation>
 <textSummary/>
 <precipType start="9" end="22">snow</precipType>
 <accumulation>
 <name>snow</name>
 <amount unitType="metric" units="cm">2</amount>
 </accumulation>
 </precipitation>
 <relativeHumidity units="%">70</relativeHumidity>
 <comfort>
 <textSummary>cold.</textSummary>
 </comfort>
 </forecast>
 <forecast>
 <period textForecastName="Tonight">Friday night</period>
 <textSummary>Cloudy. Snow beginning overnight. Wind southwest 20 km/h becoming light near midnight. Low minus 1.</textSummary>
 <cloudPrecip>
 <textSummary>Cloudy. Snow beginning overnight.</textSummary>
 </cloudPrecip>
 <abbreviatedForecast>
 <iconCode format="gif">17</iconCode>
 <pop units="%"/>
 <textSummary>Snow</textSummary>
 </abbreviatedForecast>
 <temperatures>
 <textSummary>Low minus 1.</textSummary>
 <temperature unitType="metric" units="C" class="low">-1</temperature>
 </temperatures>
 <winds>
 <textSummary>Wind southwest 20 km/h becoming light near midnight.</textSummary>
 <wind index="1" rank="major">
 <speed unitType="metric" units="km/h">20</speed>
 <gust unitType="metric" units="km/h">00</gust>
 <direction>SW</direction>
 <bearing units="degrees">22</bearing>
 </wind>
 <wind index="2" rank="major">
 <speed unitType="metric" units="km/h">15</speed>
 <gust unitType="metric" units="km/h">00</gust>
 <direction>SE</direction>
 <bearing units="degrees">14</bearing>
 </wind>
 </winds>
 <precipitation>
 <textSummary/>
 <precipType start="31" end="34">snow</precipType>
 <accumulation>
 <name>snow</name>
 <amount unitType="metric" units="cm">2</amount>
 </accumulation>
 </precipitation>
 <relativeHumidity units="%">100</relativeHumidity>
 </forecast>
 <forecast>
 <period textForecastName="Saturday">Saturday</period>
 <textSummary>Snow changing to rain in the morning. Wind southeast 20 km/h. High 8.</textSummary>
 <cloudPrecip>
 <textSummary>Snow changing to rain in the morning.</textSummary>
 </cloudPrecip>
 <abbreviatedForecast>
 <iconCode format="gif">15</iconCode>
 <pop units="%"/>
 <textSummary>Rain or snow</textSummary>
 </abbreviatedForecast>
 <temperatures>
 <textSummary>High 8.</textSummary>
 <temperature unitType="metric" units="C" class="high">8</temperature>
 </temperatures>
 <winds>
 <textSummary>Wind southeast 20 km/h.</textSummary>
 <wind index="1" rank="major">
 <speed unitType="metric" units="km/h">20</speed>
 <gust unitType="metric" units="km/h">00</gust>
 <direction>SE</direction>
 <bearing units="degrees">14</bearing>
 </wind>
 </winds>
 <precipitation>
 <textSummary/>
 <precipType start="34" end="37">snow</precipType>
 <precipType start="37" end="46">rain</precipType>
 <accumulation>
 <name>rain</name>
 <amount unitType="metric" units="mm">12</amount>
 </accumulation>
 <accumulation>
 <name>snow</name>
 <amount unitType="metric" units="cm">1</amount>
 </accumulation>
 </precipitation>
 <relativeHumidity units="%">85</relativeHumidity>
 </forecast>
 <forecast>
 <period textForecastName="Saturday night">Saturday night</period>
 <textSummary>Showers. Low plus 5.</textSummary>
 <cloudPrecip>
 <textSummary>Showers.</textSummary>
 </cloudPrecip>
 <abbreviatedForecast>
 <iconCode format="gif">12</iconCode>
 <pop units="%"/>
 <textSummary>Showers</textSummary>
 </abbreviatedForecast>
 <temperatures>
 <textSummary>Low plus 5.</textSummary>
 <temperature unitType="metric" units="C" class="low">5</temperature>
 </temperatures>
 <winds/>
 <precipitation>
 <textSummary/>
 <precipType start="46" end="58">rain</precipType>
 </precipitation>
 <relativeHumidity units="%">95</relativeHumidity>
 </forecast>
 <forecast>
 <period textForecastName="Sunday">Sunday</period>
 <textSummary>Showers. Windy. High plus 5.</textSummary>
 <cloudPrecip>
 <textSummary>Showers.</textSummary>
 </cloudPrecip>
 <abbreviatedForecast>
 <iconCode format="gif">12</iconCode>
 <pop units="%"/>
 <textSummary>Showers</textSummary>
 </abbreviatedForecast>
 <temperatures>
 <textSummary>High plus 5.</textSummary>
 <temperature unitType="metric" units="C" class="high">5</temperature>
 </temperatures>
 <winds>
 <textSummary>Windy.</textSummary>
 <wind index="1" rank="major">
 <speed unitType="metric" units="km/h">20</speed>
 <gust unitType="metric" units="km/h">00</gust>
 <direction>N</direction>
 <bearing units="degrees">36</bearing>
 </wind>
 <wind index="2" rank="major">
 <speed unitType="metric" units="km/h">40</speed>
 <gust unitType="metric" units="km/h">60</gust>
 <direction>N</direction>
 <bearing units="degrees">36</bearing>
 </wind>
 </winds>
 <precipitation>
 <textSummary/>
 <precipType start="58" end="60">rain</precipType>
 <precipType start="66" end="70">rain</precipType>
 </precipitation>
 <relativeHumidity units="%">80</relativeHumidity>
 </forecast>
 <forecast>
 <period textForecastName="Sunday night">Sunday night</period>
 <textSummary>Cloudy periods with 40 percent chance of showers. Low minus 3.</textSummary>
 <cloudPrecip>
 <textSummary>Cloudy periods with 40 percent chance of showers.</textSummary>
 </cloudPrecip>
 <abbreviatedForecast>
 <iconCode format="gif">36</iconCode>
 <pop units="%">40</pop>
 <textSummary>Chance of showers</textSummary>
 </abbreviatedForecast>
 <temperatures>
 <textSummary>Low minus 3.</textSummary>
 <temperature unitType="metric" units="C" class="low">-3</temperature>
 </temperatures>
 <winds/>
 <precipitation>
 <textSummary/>
 <precipType start="70" end="72">rain</precipType>
 </precipitation>
 <relativeHumidity units="%">85</relativeHumidity>
 </forecast>
 <forecast>
 <period textForecastName="Monday">Monday</period>
 <textSummary>A mix of sun and cloud. High zero.</textSummary>
 <cloudPrecip>
 <textSummary>A mix of sun and cloud.</textSummary>
 </cloudPrecip>
 <abbreviatedForecast>
 <iconCode format="gif">02</iconCode>
 <pop units="%"/>
 <textSummary>A mix of sun and cloud</textSummary>
 </abbreviatedForecast>
 <temperatures>
 <textSummary>High zero.</textSummary>
 <temperature unitType="metric" units="C" class="high">0</temperature>
 </temperatures>
 <winds/>
 <precipitation>
 <textSummary/>
 <precipType start="" end=""/>
 </precipitation>
 <relativeHumidity units="%">70</relativeHumidity>
 </forecast>
 <forecast>
 <period textForecastName="Monday night">Monday night</period>
 <textSummary>Clear. Low minus 2.</textSummary>
 <cloudPrecip>
 <textSummary>Clear.</textSummary>
 </cloudPrecip>
 <abbreviatedForecast>
 <iconCode format="gif">30</iconCode>
 <pop units="%"/>
 <textSummary>Clear</textSummary>
 </abbreviatedForecast>
 <temperatures>
 <textSummary>Low minus 2.</textSummary>
 <temperature unitType="metric" units="C" class="low">-2</temperature>
 </temperatures>
 <winds/>
 <precipitation>
 <textSummary/>
 <precipType start="" end=""/>
 </precipitation>
 <relativeHumidity units="%">70</relativeHumidity>
 </forecast>
 <forecast>
 <period textForecastName="Tuesday">Tuesday</period>
 <textSummary>A mix of sun and cloud. High plus 4.</textSummary>
 <cloudPrecip>
 <textSummary>A mix of sun and cloud.</textSummary>
 </cloudPrecip>
 <abbreviatedForecast>
 <iconCode format="gif">02</iconCode>
 <pop units="%"/>
 <textSummary>A mix of sun and cloud</textSummary>
 </abbreviatedForecast>
 <temperatures>
 <textSummary>High plus 4.</textSummary>
 <temperature unitType="metric" units="C" class="high">4</temperature>
 </temperatures>
 <winds/>
 <precipitation>
 <textSummary/>
 <precipType start="" end=""/>
 </precipitation>
 <relativeHumidity units="%">55</relativeHumidity>
 </forecast>
 <forecast>
 <period textForecastName="Tuesday night">Tuesday night</period>
 <textSummary>Cloudy with 60 percent chance of showers. Low plus 2.</textSummary>
 <cloudPrecip>
 <textSummary>Cloudy with 60 percent chance of showers.</textSummary>
 </cloudPrecip>
 <abbreviatedForecast>
 <iconCode format="gif">12</iconCode>
 <pop units="%">60</pop>
 <textSummary>Chance of showers</textSummary>
 </abbreviatedForecast>
 <temperatures>
 <textSummary>Low plus 2.</textSummary>
 <temperature unitType="metric" units="C" class="low">2</temperature>
 </temperatures>
 <winds/>
 <precipitation>
 <textSummary/>
 <precipType start="126" end="130">rain</precipType>
 </precipitation>
 <relativeHumidity units="%">85</relativeHumidity>
 </forecast>
 <forecast>
 <period textForecastName="Wednesday">Wednesday</period>
 <textSummary>Cloudy with 60 percent chance of showers. High plus 4.</textSummary>
 <cloudPrecip>
 <textSummary>Cloudy with 60 percent chance of showers.</textSummary>
 </cloudPrecip>
 <abbreviatedForecast>
 <iconCode format="gif">12</iconCode>
 <pop units="%">60</pop>
 <textSummary>Chance of showers</textSummary>
 </abbreviatedForecast>
 <temperatures>
 <textSummary>High plus 4.</textSummary>
 <temperature unitType="metric" units="C" class="high">4</temperature>
 </temperatures>
 <winds/>
 <precipitation>
 <textSummary/>
 <precipType start="130" end="142">rain</precipType>
 </precipitation>
 <relativeHumidity units="%">95</relativeHumidity>
 </forecast>
 <forecast>
 <period textForecastName="Wednesday night">Wednesday night</period>
 <textSummary>Rain. Low plus 2.</textSummary>
 <cloudPrecip>
 <textSummary>Rain.</textSummary>
 </cloudPrecip>
 <abbreviatedForecast>
 <iconCode format="gif">12</iconCode>
 <pop units="%"/>
 <textSummary>Rain</textSummary>
 </abbreviatedForecast>
 <temperatures>
 <textSummary>Low plus 2.</textSummary>
 <temperature unitType="metric" units="C" class="low">2</temperature>
 </temperatures>
 <winds/>
 <precipitation>
 <textSummary/>
 <precipType start="142" end="154">rain</precipType>
 </precipitation>
 <relativeHumidity units="%">95</relativeHumidity>
 </forecast>
 <forecast>
 <period textForecastName="Thursday">Thursday</period>
 <textSummary>Cloudy with 70 percent chance of showers. High plus 2.</textSummary>
 <cloudPrecip>
 <textSummary>Cloudy with 70 percent chance of showers.</textSummary>
 </cloudPrecip>
 <abbreviatedForecast>
 <iconCode format="gif">12</iconCode>
 <pop units="%">70</pop>
 <textSummary>Chance of showers</textSummary>
 </abbreviatedForecast>
 <temperatures>
 <textSummary>High plus 2.</textSummary>
 <temperature unitType="metric" units="C" class="high">2</temperature>
 </temperatures>
 <winds/>
 <precipitation>
 <textSummary/>
 <precipType start="154" end="156">rain</precipType>
 <precipType start="162" end="166">rain</precipType>
 </precipitation>
 <relativeHumidity units="%">95</relativeHumidity>
 </forecast>
 </forecastGroup>
 <yesterdayConditions>
 <temperature unitType="metric" units="C" class="high">3.6</temperature>
 <temperature unitType="metric" units="C" class="low">-1.1</temperature>
 <precip unitType="metric" units="mm">4.3</precip>
 </yesterdayConditions>
 <riseSet>
 <disclaimer>The information provided here, for the times of the rise and set of the sun, is an estimate included as a convenience to our clients. Values shown here may differ from the official sunrise/sunset data available from (http://hia-iha.nrc-cnrc.gc.ca/sunrise_e.html)</disclaimer>
 <dateTime name="sunrise" zone="UTC" UTCOffset="0">
 <year>2016</year>
 <month name="October">10</month>
 <day name="Friday">14</day>
 <hour>11</hour>
 <minute>39</minute>
 <timeStamp>20161014113900</timeStamp>
 <textSummary>Friday October 14, 2016 at 11:39 UTC</textSummary>
 </dateTime>
 <dateTime name="sunrise" zone="EDT" UTCOffset="-4">
 <year>2016</year>
 <month name="October">10</month>
 <day name="Friday">14</day>
 <hour>07</hour>
 <minute>39</minute>
 <timeStamp>20161014073900</timeStamp>
 <textSummary>Friday October 14, 2016 at 07:39 EDT</textSummary>
 </dateTime>
 <dateTime name="sunset" zone="UTC" UTCOffset="0">
 <year>2016</year>
 <month name="October">10</month>
 <day name="Friday">14</day>
 <hour>22</hour>
 <minute>14</minute>
 <timeStamp>20161014221400</timeStamp>
 <textSummary>Friday October 14, 2016 at 22:14 UTC</textSummary>
 </dateTime>
 <dateTime name="sunset" zone="EDT" UTCOffset="-4">
 <year>2016</year>
 <month name="October">10</month>
 <day name="Friday">14</day>
 <hour>18</hour>
 <minute>14</minute>
 <timeStamp>20161014181400</timeStamp>
 <textSummary>Friday October 14, 2016 at 18:14 EDT</textSummary>
 </dateTime>
 </riseSet>
 <almanac>
 <temperature class="extremeMax" period="1925-2013" unitType="metric" units="C" year="2011">18.6</temperature>
 <temperature class="extremeMin" period="1925-2013" unitType="metric" units="C" year="1998">-6.3</temperature>
 <temperature class="normalMax" unitType="metric" units="C">5.1</temperature>
 <temperature class="normalMin" unitType="metric" units="C">-0.3</temperature>
 <temperature class="normalMean" unitType="metric" units="C">2.4</temperature>
 <precipitation class="extremeRainfall" period="1925-2013" unitType="metric" units="mm" year="1951">32.0</precipitation>
 <precipitation class="extremeSnowfall" period="1928-2013" unitType="metric" units="cm" year="1983">15.4</precipitation>
 <precipitation class="extremePrecipitation" period="1928-2013" unitType="metric" units="mm" year="1951">32.0</precipitation>
 <precipitation class="extremeSnowOnGround" period="1955-2013" unitType="metric" units="cm" year="1972">10.0</precipitation>
 <pop units="%">70.0</pop>
 </almanac>
 </siteData>

