<?xml version='1.0' encoding='ISO-8859-1'?>
 <siteData xmlns:xsi="http://www.w3.org/2001/XMLSchema-instance" xsi:noNamespaceSchemaLocation="http://dd.meteo.gc.ca/citypage_weather/schema/site.xsd">
 <license>http://dd.meteo.gc.ca/doc/LICENCE_GENERAL.txt</license>
 <dateTime name="xmlCreation" zone="UTC" UTCOffset="0">
 <year>2016</year>
 <month name="octobre">10</month>
 <day name="vendredi">14</day>
 <hour>14</hour>
 <minute>06</minute>
 <timeStamp>20161014140600</timeStamp>
 <textSummary>14 octobre 2016 14h06 UTC</textSummary>
 </dateTime>
 <dateTime name="xmlCreation" zone="HAE" UTCOffset="-4">
 <year>2016</year>
 <month name="octobre">10</month>
 <day name="vendredi">14</day>
 <hour>10</hour>
 <minute>06</minute>
 <timeStamp>20161014100600</timeStamp>
 <textSummary>14 octobre 2016 10h06 HAE</textSummary>
 </dateTime>
 <location>
 <continent>Amérique du Nord</continent>
 <country code="ca">Canada</country>
 <province code="qc">Québec</province>
 <name code="s0000244" lat="46.38N" lon="75.97O">Maniwaki</name>
 <region>Haute-Gatineau - Lièvre - Papineau</region>
 </location>
 <warnings/>
 <currentConditions>
 <station code="wmj" lat="46.27N" lon="75.99O">Aéroport de Maniwaki</station>
 <dateTime name="observation" zone="UTC" UTCOffset="0">
 <year>2016</year>
 <month name="octobre">10</month>
 <day name="vendredi">14</day>
 <hour>14</hour>
 <minute>00</minute>
 <timeStamp>20161014140000</timeStamp>
 <textSummary>14 octobre 2016 14h00 UTC</textSummary>
 </dateTime>
 <dateTime name="observation" zone="HAE" UTCOffset="-4">
 <year>2016</year>
 <month name="octobre">10</month>
 <day name="vendredi">14</day>
 <hour>10</hour>
 <minute>00</minute>
 <timeStamp>20161014100000</timeStamp>
 <textSummary>14 octobre 2016 10h00 HAE</textSummary>
 </dateTime>
 <condition/>
 <iconCode format="gif"/>
 <temperature unitType="metric" units="C">2.8</temperature>
 <dewpoint unitType="metric" units="C">1.2</dewpoint>
 <pressure unitType="metric" units="kPa" change="0.13" tendency="à la hausse">103.0</pressure>
 <visibility unitType="metric" units="km"/>
 <relativeHumidity units="%">89</relativeHumidity>
 <wind>
 <speed unitType="metric" units="km/h">7</speed>
 <gust unitType="metric" units="km/h"/>
 <direction>SSE</direction>
 <bearing units="degrees">148.1</bearing>
 </wind>
 </currentConditions>
 <forecastGroup>
 <dateTime name="forecastIssue" zone="UTC" UTCOffset="0">
 <year>2016</year>
 <month name="octobre">10</month>
 <day name="vendredi">14</day>
 <hour>09</hour>
 <minute>00</minute>
 <timeStamp>20161014090000</timeStamp>
 <textSummary>14 octobre 2016 09h00 UTC</textSummary>
 </dateTime>
 <dateTime name="forecastIssue" zone="HAE" UTCOffset="-4">
 <year>2016</year>
 <month name="octobre">10</month>
 <day name="vendredi">14</day>
 <hour>05</hour>
 <minute>00</minute>
 <timeStamp>20161014050000</timeStamp>
 <textSummary>14 octobre 2016 05h00 HAE</textSummary>
 </dateTime>
 <regionalNormals>
 <textSummary>Minimum plus 1. Maximum 11.</textSummary>
 <temperature unitType="metric" units="C" class="high">11</temperature>
 <temperature unitType="metric" units="C" class="low">1</temperature>
 </regionalNormals>
 <forecast>
 <period textForecastName="Aujourd'hui">vendredi</period>
 <textSummary>Alternance de soleil et de nuages. Nappes de brouillard se dissipant ce matin. Maximum 9. Indice UV de 3 ou modéré.</textSummary>
 <cloudPrecip>
 <textSummary>Alternance de soleil et de nuages.</textSummary>
 </cloudPrecip>
 <abbreviatedForecast>
 <iconCode format="gif">02</iconCode>
 <pop units="%"/>
 <textSummary>Alternance de soleil et de nuages</textSummary>
 </abbreviatedForecast>
 <temperatures>
 <textSummary>Maximum 9.</textSummary>
 <temperature unitType="metric" units="C" class="high">9</temperature>
 </temperatures>
 <winds/>
 <precipitation>
 <textSummary/>
 <precipType start="" end=""/>
 </precipitation>
 <visibility>
 <otherVisib cause="other">
 <textSummary>Nappes de brouillard se dissipant ce matin.</textSummary>
 </otherVisib>
 </visibility>
 <uv category="modéré">
 <index>3</index>
 <textSummary>Indice UV de 3 ou modéré.</textSummary>
 </uv>
 <relativeHumidity units="%">65</relativeHumidity>
 </forecast>
 <forecast>
 <period textForecastName="Ce soir et cette nuit">ce soir et cette nuit</period>
 <textSummary>Partiellement nuageux. Minimum plus 4.</textSummary>
 <cloudPrecip>
 <textSummary>Partiellement nuageux.</textSummary>
 </cloudPrecip>
 <abbreviatedForecast>
 <iconCode format="gif">32</iconCode>
 <pop units="%"/>
 <textSummary>Partiellement nuageux</textSummary>
 </abbreviatedForecast>
 <temperatures>
 <textSummary>Minimum plus 4.</textSummary>
 <temperature unitType="metric" units="C" class="low">4</temperature>
 </temperatures>
 <winds/>
 <precipitation>
 <textSummary/>
 <precipType start="" end=""/>
 </precipitation>
 <relativeHumidity units="%">80</relativeHumidity>
 </forecast>
 <forecast>
 <period textForecastName="Samedi">samedi</period>
 <textSummary>Alternance de soleil et de nuages. Vents devenant du sud à 20 km/h en mi-journée. Maximum 16.</textSummary>
 <cloudPrecip>
 <textSummary>Alternance de soleil et de nuages.</textSummary>
 </cloudPrecip>
 <abbreviatedForecast>
 <iconCode format="gif">02</iconCode>
 <pop units="%"/>
 <textSummary>Alternance de soleil et de nuages</textSummary>
 </abbreviatedForecast>
 <temperatures>
 <textSummary>Maximum 16.</textSummary>
 <temperature unitType="metric" units="C" class="high">16</temperature>
 </temperatures>
 <winds>
 <textSummary>Vents devenant du sud à 20 km/h en mi-journée.</textSummary>
 <wind index="1" rank="minor">
 <speed unitType="metric" units="km/h">10</speed>
 <gust unitType="metric" units="km/h">00</gust>
 <direction>S</direction>
 <bearing units="degrees">18</bearing>
 </wind>
 <wind index="2" rank="major">
 <speed unitType="metric" units="km/h">15</speed>
 <gust unitType="metric" units="km/h">00</gust>
 <direction>S</direction>
 <bearing units="degrees">18</bearing>
 </wind>
 <wind index="3" rank="major">
 <speed unitType="metric" units="km/h">20</speed>
 <gust unitType="metric" units="km/h">00</gust>
 <direction>S</direction>
 <bearing units="degrees">18</bearing>
 </wind>
 </winds>
 <precipitation>
 <textSummary/>
 <precipType start="" end=""/>
 </precipitation>
 <relativeHumidity units="%">50</relativeHumidity>
 </forecast>
 <forecast>
 <period textForecastName="Samedi soir et nuit">samedi soir et nuit</period>
 <textSummary>Averses. Minimum 13.</textSummary>
 <cloudPrecip>
 <textSummary>Averses.</textSummary>
 </cloudPrecip>
 <abbreviatedForecast>
 <iconCode format="gif">12</iconCode>
 <pop units="%"/>
 <textSummary>Averses</textSummary>
 </abbreviatedForecast>
 <temperatures>
 <textSummary>Minimum 13.</textSummary>
 <temperature unitType="metric" units="C" class="low">13</temperature>
 </temperatures>
 <winds/>
 <precipitation>
 <textSummary/>
 <precipType start="54" end="58">pluie</precipType>
 </precipitation>
 <relativeHumidity units="%">95</relativeHumidity>
 </forecast>
 <forecast>
 <period textForecastName="Dimanche">dimanche</period>
 <textSummary>Averses. Maximum 20.</textSummary>
 <cloudPrecip>
 <textSummary>Averses.</textSummary>
 </cloudPrecip>
 <abbreviatedForecast>
 <iconCode format="gif">12</iconCode>
 <pop units="%"/>
 <textSummary>Averses</textSummary>
 </abbreviatedForecast>
 <temperatures>
 <textSummary>Maximum 20.</textSummary>
 <temperature unitType="metric" units="C" class="high">20</temperature>
 </temperatures>
 <winds/>
 <precipitation>
 <textSummary/>
 <precipType start="58" end="66">pluie</precipType>
 </precipitation>
 <relativeHumidity units="%">60</relativeHumidity>
 </forecast>
 <forecast>
 <period textForecastName="Dimanche soir et nuit">dimanche soir et nuit</period>
 <textSummary>Dégagé. Minimum plus 2.</textSummary>
 <cloudPrecip>
 <textSummary>Dégagé.</textSummary>
 </cloudPrecip>
 <abbreviatedForecast>
 <iconCode format="gif">30</iconCode>
 <pop units="%"/>
 <textSummary>Dégagé</textSummary>
 </abbreviatedForecast>
 <temperatures>
 <textSummary>Minimum plus 2.</textSummary>
 <temperature unitType="metric" units="C" class="low">2</temperature>
 </temperatures>
 <winds/>
 <precipitation>
 <textSummary/>
 <precipType start="" end=""/>
 </precipitation>
 <relativeHumidity units="%">85</relativeHumidity>
 </forecast>
 <forecast>
 <period textForecastName="Lundi">lundi</period>
 <textSummary>Ennuagement. Maximum 14.</textSummary>
 <cloudPrecip>
 <textSummary>Ennuagement.</textSummary>
 </cloudPrecip>
 <abbreviatedForecast>
 <iconCode format="gif">02</iconCode>
 <pop units="%"/>
 <textSummary>Alternance de soleil et de nuages</textSummary>
 </abbreviatedForecast>
 <temperatures>
 <textSummary>Maximum 14.</textSummary>
 <temperature unitType="metric" units="C" class="high">14</temperature>
 </temperatures>
 <winds/>
 <precipitation>
 <textSummary/>
 <precipType start="93" end="94">pluie</precipType>
 </precipitation>
 <relativeHumidity units="%">65</relativeHumidity>
 </forecast>
 <forecast>
 <period textForecastName="Lundi soir et nuit">lundi soir et nuit</period>
 <textSummary>Pluie intermittente. Minimum 8.</textSummary>
 <cloudPrecip>
 <textSummary>Pluie intermittente.</textSummary>
 </cloudPrecip>
 <abbreviatedForecast>
 <iconCode format="gif">12</iconCode>
 <pop units="%"/>
 <textSummary>Pluie intermittente</textSummary>
 </abbreviatedForecast>
 <temperatures>
 <textSummary>Minimum 8.</textSummary>
 <temperature unitType="metric" units="C" class="low">8</temperature>
 </temperatures>
 <winds/>
 <precipitation>
 <textSummary/>
 <precipType start="94" end="106">pluie</precipType>
 </precipitation>
 <relativeHumidity units="%">95</relativeHumidity>
 </forecast>
 <forecast>
 <period textForecastName="Mardi">mardi</period>
 <textSummary>Averses. Maximum 12.</textSummary>
 <cloudPrecip>
 <textSummary>Averses.</textSummary>
 </cloudPrecip>
 <abbreviatedForecast>
 <iconCode format="gif">12</iconCode>
 <pop units="%"/>
 <textSummary>Averses</textSummary>
 </abbreviatedForecast>
 <temperatures>
 <textSummary>Maximum 12.</textSummary>
 <temperature unitType="metric" units="C" class="high">12</temperature>
 </temperatures>
 <winds/>
 <precipitation>
 <textSummary/>
 <precipType start="106" end="108">pluie</precipType>
 <precipType start="114" end="118">pluie</precipType>
 </precipitation>
 <relativeHumidity units="%">85</relativeHumidity>
 </forecast>
 <forecast>
 <period textForecastName="Mardi soir et nuit">mardi soir et nuit</period>
 <textSummary>Nuageux avec 70 pour cent de probabilité d'averses. Minimum 11.</textSummary>
 <cloudPrecip>
 <textSummary>Nuageux avec 70 pour cent de probabilité d'averses.</textSummary>
 </cloudPrecip>
 <abbreviatedForecast>
 <iconCode format="gif">12</iconCode>
 <pop units="%">70</pop>
 <textSummary>Possibilité d'averses</textSummary>
 </abbreviatedForecast>
 <temperatures>
 <textSummary>Minimum 11.</textSummary>
 <temperature unitType="metric" units="C" class="low">11</temperature>
 </temperatures>
 <winds/>
 <precipitation>
 <textSummary/>
 <precipType start="118" end="130">pluie</precipType>
 </precipitation>
 <relativeHumidity units="%">100</relativeHumidity>
 </forecast>
 <forecast>
 <period textForecastName="Mercredi">mercredi</period>
 <textSummary>Nuageux avec 60 pour cent de probabilité d'averses. Maximum 18.</textSummary>
 <cloudPrecip>
 <textSummary>Nuageux avec 60 pour cent de probabilité d'averses.</textSummary>
 </cloudPrecip>
 <abbreviatedForecast>
 <iconCode format="gif">12</iconCode>
 <pop units="%">60</pop>
 <textSummary>Possibilité d'averses</textSummary>
 </abbreviatedForecast>
 <temperatures>
 <textSummary>Maximum 18.</textSummary>
 <temperature unitType="metric" units="C" class="high">18</temperature>
 </temperatures>
 <winds/>
 <precipitation>
 <textSummary/>
 <precipType start="130" end="138">pluie</precipType>
 </precipitation>
 <relativeHumidity units="%">80</relativeHumidity>
 </forecast>
 <forecast>
 <period textForecastName="Mercredi soir et nuit">mercredi soir et nuit</period>
 <textSummary>Nuageux. Minimum 6.</textSummary>
 <cloudPrecip>
 <textSummary>Nuageux.</textSummary>
 </cloudPrecip>
 <abbreviatedForecast>
 <iconCode format="gif">10</iconCode>
 <pop units="%"/>
 <textSummary>Nuageux</textSummary>
 </abbreviatedForecast>
 <temperatures>
 <textSummary>Minimum 6.</textSummary>
 <temperature unitType="metric" units="C" class="low">6</temperature>
 </temperatures>
 <winds/>
 <precipitation>
 <textSummary/>
 <precipType start="" end=""/>
 </precipitation>
 <relativeHumidity units="%">100</relativeHumidity>
 </forecast>
 <forecast>
 <period textForecastName="Jeudi">jeudi</period>
 <textSummary>Nuageux. Maximum 13.</textSummary>
 <cloudPrecip>
 <textSummary>Nuageux.</textSummary>
 </cloudPrecip>
 <abbreviatedForecast>
 <iconCode format="gif">10</iconCode>
 <pop units="%"/>
 <textSummary>Nuageux</textSummary>
 </abbreviatedForecast>
 <temperatures>
 <textSummary>Maximum 13.</textSummary>
 <temperature unitType="metric" units="C" class="high">13</temperature>
 </temperatures>
 <winds/>
 <precipitation>
 <textSummary/>
 <precipType start="" end=""/>
 </precipitation>
 <relativeHumidity units="%">75</relativeHumidity>
 </forecast>
 </forecastGroup>
 <yesterdayConditions>
 <temperature unitType="metric" units="C" class="high">15.3</temperature>
 <temperature unitType="metric" units="C" class="low">-1.9</temperature>
 <precip unitType="metric" units="mm">0.0</precip>
 </yesterdayConditions>
 <riseSet>
 <disclaimer>Les heures de lever et coucher du soleil sont une estimation seulement et peuvent être différentes des heures officielles de lever et coucher du soleil disponibles ici ( http://hia-iha.nrc-cnrc.gc.ca/sunrise_f.html )</disclaimer>
 <dateTime name="sunrise" zone="UTC" UTCOffset="0">
 <year>2016</year>
 <month name="octobre">10</month>
 <day name="vendredi">14</day>
 <hour>11</hour>
 <minute>20</minute>
 <timeStamp>20161014112000</timeStamp>
 <textSummary>14 octobre 2016 11h20 UTC</textSummary>
 </dateTime>
 <dateTime name="sunrise" zone="HAE" UTCOffset="-4">
 <year>2016</year>
 <month name="octobre">10</month>
 <day name="vendredi">14</day>
 <hour>07</hour>
 <minute>20</minute>
 <timeStamp>20161014072000</timeStamp>
 <textSummary>14 octobre 2016 07h20 HAE</textSummary>
 </dateTime>
 <dateTime name="sunset" zone="UTC" UTCOffset="0">
 <year>2016</year>
 <month name="octobre">10</month>
 <day name="vendredi">14</day>
 <hour>22</hour>
 <minute>19</minute>
 <timeStamp>20161014221900</timeStamp>
 <textSummary>14 octobre 2016 22h19 UTC</textSummary>
 </dateTime>
 <dateTime name="sunset" zone="HAE" UTCOffset="-4">
 <year>2016</year>
 <month name="octobre">10</month>
 <day name="vendredi">14</day>
 <hour>18</hour>
 <minute>19</minute>
 <timeStamp>20161014181900</timeStamp>
 <textSummary>14 octobre 2016 18h19 HAE</textSummary>
 </dateTime>
 </riseSet>
 <almanac>
 <temperature class="extremeMax" period="1993-2015" unitType="metric" units="C" year="2014">24.4</temperature>
 <temperature class="extremeMin" period="1993-2015" unitType="metric" units="C" year="1993">-7.2</temperature>
 <temperature class="normalMax" unitType="metric" units="C"/>
 <temperature class="normalMin" unitType="metric" units="C"/>
 <temperature class="normalMean" unitType="metric" units="C"/>
 <precipitation class="extremeRainfall" period="-" unitType="metric" units="mm" year=""/>
 <precipitation class="extremeSnowfall" period="-" unitType="metric" units="cm" year=""/>
 <precipitation class="extremePrecipitation" period="1993-2015" unitType="metric" units="mm" year="2012">36.0</precipitation>
 <precipitation class="extremeSnowOnGround" period="-" unitType="metric" units="cm" year=""/>
 <pop units="%"/>
 </almanac>
 </siteData>

